Workbook

Sheet Dashboard
A1: MONTE CARLO COST MODEL
A2: ='Setup'!C4
A3: ="All figures in "&'Setup'!C5
A4: Currency | B4: Years | C4: Iterations | D4: Confidence | E4: Discount | F4: Checks
A5: ='Setup'!C5 | B5: ='Setup'!C8 | C5: ='Setup'!C9 | D5: ='Setup'!C10 | E5: ='Setup'!C11 | F5: ='Checks'!$B$13
A7: ▶ Run Simulation | D7: 📅 Apply Years | F7: ⬇ Export Report
A8: Buttons need the VBA modules (vba/). Save as .xlsm. See vba/VBA_SETUP.md.
A10: KEY OUTPUTS (filled by the macro)
A11: Base Cost (ML) | C11: Expected Cost | E11: Expected Risk | G11: Total Expected
A14: P50 | C14: P70 | E14: P80 | G14: P90
A17: Contingency | C17: Recommended Budget | E17: NPV @ confidence | G17: P95

Sheet Setup
B1: MODEL SETUP
B2: Yellow cells are inputs. Run the simulation from the Dashboard (or Alt+F8 ▸ RunSimulation).
B4: Project name | C4: Sample Construction Project
B5: Currency | C5: SAR
B6: Base year | C6: 2025
B7: Start year | C7: 2025
B8: Number of years | C8: 5
B9: Iterations | C9: 10000
B10: Confidence level | C10: P80
B11: Discount rate | C11: 0.08
B12: VAT treatment | C12: Excluded | E12: ↳ inflation is per year on the Inflation sheet
B13: Prepared by
B14: Date
B16: Confidence (numeric) | C16: =VALUE(MID(C10,2,2))/100

Sheet Cost Lines
A1: COST LINES — 3-Point Estimates (add rows freely; the macro reads them all)
A2: ➕ Add → AddCostLine | D2: 🗑 Delete selected → DeleteCostLine
A3: No. | B3: Cost Item | C3: Category | D3: Description | E3: Unit | F3: Quantity | G3: Min Unit Cost | H3: Most Likely Unit Cost | I3: Max Unit Cost | J3: Min Total Cost | K3: Most Likely Total Cost | L3: Max Total Cost | M3: Distribution | N3: Include? | O3: Notes
A4: =ROW()-3 | B4: Site Preparation | C4: Civil | D4: Site Preparation works | E4: LS | F4: 1 | G4: 28000 | H4: 38000 | I4: 60000 | J4: =F4*G4 | K4: =F4*H4 | L4: =F4*I4 | M4: Triangular | N4: Yes
A5: =ROW()-3 | B5: Foundations | C5: Civil | D5: Foundations works | E5: LS | F5: 1 | G5: 45000 | H5: 55000 | I5: 75000 | J5: =F5*G5 | K5: =F5*H5 | L5: =F5*I5 | M5: Triangular | N5: Yes
A6: =ROW()-3 | B6: Superstructure | C6: Structural | D6: Superstructure works | E6: LS | F6: 1 | G6: 90000 | H6: 120000 | I6: 170000 | J6: =F6*G6 | K6: =F6*H6 | L6: =F6*I6 | M6: Pert | N6: Yes
A7: =ROW()-3 | B7: MEP Systems | C7: MEP | D7: MEP Systems works | E7: LS | F7: 1 | G7: 60000 | H7: 80000 | I7: 115000 | J7: =F7*G7 | K7: =F7*H7 | L7: =F7*I7 | M7: Pert | N7: Yes
A8: =ROW()-3 | B8: Finishes | C8: Architectural | D8: Finishes works | E8: LS | F8: 1 | G8: 30000 | H8: 45000 | I8: 70000 | J8: =F8*G8 | K8: =F8*H8 | L8: =F8*I8 | M8: Triangular | N8: Yes
A9: =ROW()-3 | B9: Project Management | C9: PM | D9: Project Management works | E9: LS | F9: 1 | G9: 20000 | H9: 28000 | I9: 40000 | J9: =F9*G9 | K9: =F9*H9 | L9: =F9*I9 | M9: Normal | N9: Yes

Sheet Cost Profiling
A1: COST PROFILING — % per year (rows must total 100%)
A3: No. | B3: Cost Item | C3: FY1 | D3: FY2 | E3: FY3 | F3: FY4 | G3: FY5 | H3: FY6 | I3: FY7 | J3: FY8 | K3: FY9 | L3: FY10 | M3: FY11 | N3: FY12 | O3: FY13 | P3: FY14 | Q3: FY15 | R3: FY16 | S3: FY17 | T3: FY18 | U3: FY19 | V3: FY20 | W3: FY21 | X3: FY22 | Y3: FY23 | Z3: FY24 | AA3: FY25 | AB3: FY26 | AC3: FY27 | AD3: FY28 | AE3: FY29 | AF3: FY30 | AG3: Total %
A4: ='Cost Lines'!A4 | B4: ='Cost Lines'!B4 | C4: 0.33333333 | D4: 0.26666667 | E4: 0.2 | F4: 0.13333333 | G4: 0.066666667 | H4: 0 | I4: 0 | J4: 0 | K4: 0 | L4: 0 | M4: 0 | N4: 0 | O4: 0 | P4: 0 | Q4: 0 | R4: 0 | S4: 0 | T4: 0 | U4: 0 | V4: 0 | W4: 0 | X4: 0 | Y4: 0 | Z4: 0 | AA4: 0 | AB4: 0 | AC4: 0 | AD4: 0 | AE4: 0 | AF4: 0 | AG4: =SUM(C4:INDEX(C4:AF4,1,'Setup'!$C$8))
A5: ='Cost Lines'!A5 | B5: ='Cost Lines'!B5 | C5: 0.33333333 | D5: 0.26666667 | E5: 0.2 | F5: 0.13333333 | G5: 0.066666667 | H5: 0 | I5: 0 | J5: 0 | K5: 0 | L5: 0 | M5: 0 | N5: 0 | O5: 0 | P5: 0 | Q5: 0 | R5: 0 | S5: 0 | T5: 0 | U5: 0 | V5: 0 | W5: 0 | X5: 0 | Y5: 0 | Z5: 0 | AA5: 0 | AB5: 0 | AC5: 0 | AD5: 0 | AE5: 0 | AF5: 0 | AG5: =SUM(C5:INDEX(C5:AF5,1,'Setup'!$C$8))
A6: ='Cost Lines'!A6 | B6: ='Cost Lines'!B6 | C6: 0.11111111 | D6: 0.22222222 | E6: 0.33333333 | F6: 0.22222222 | G6: 0.11111111 | H6: 0 | I6: 0 | J6: 0 | K6: 0 | L6: 0 | M6: 0 | N6: 0 | O6: 0 | P6: 0 | Q6: 0 | R6: 0 | S6: 0 | T6: 0 | U6: 0 | V6: 0 | W6: 0 | X6: 0 | Y6: 0 | Z6: 0 | AA6: 0 | AB6: 0 | AC6: 0 | AD6: 0 | AE6: 0 | AF6: 0 | AG6: =SUM(C6:INDEX(C6:AF6,1,'Setup'!$C$8))
A7: ='Cost Lines'!A7 | B7: ='Cost Lines'!B7 | C7: 0.066666667 | D7: 0.13333333 | E7: 0.2 | F7: 0.26666667 | G7: 0.33333333 | H7: 0 | I7: 0 | J7: 0 | K7: 0 | L7: 0 | M7: 0 | N7: 0 | O7: 0 | P7: 0 | Q7: 0 | R7: 0 | S7: 0 | T7: 0 | U7: 0 | V7: 0 | W7: 0 | X7: 0 | Y7: 0 | Z7: 0 | AA7: 0 | AB7: 0 | AC7: 0 | AD7: 0 | AE7: 0 | AF7: 0 | AG7: =SUM(C7:INDEX(C7:AF7,1,'Setup'!$C$8))
A8: ='Cost Lines'!A8 | B8: ='Cost Lines'!B8 | C8: 0.066666667 | D8: 0.13333333 | E8: 0.2 | F8: 0.26666667 | G8: 0.33333333 | H8: 0 | I8: 0 | J8: 0 | K8: 0 | L8: 0 | M8: 0 | N8: 0 | O8: 0 | P8: 0 | Q8: 0 | R8: 0 | S8: 0 | T8: 0 | U8: 0 | V8: 0 | W8: 0 | X8: 0 | Y8: 0 | Z8: 0 | AA8: 0 | AB8: 0 | AC8: 0 | AD8: 0 | AE8: 0 | AF8: 0 | AG8: =SUM(C8:INDEX(C8:AF8,1,'Setup'!$C$8))
A9: ='Cost Lines'!A9 | B9: ='Cost Lines'!B9 | C9: 0.2 | D9: 0.2 | E9: 0.2 | F9: 0.2 | G9: 0.2 | H9: 0 | I9: 0 | J9: 0 | K9: 0 | L9: 0 | M9: 0 | N9: 0 | O9: 0 | P9: 0 | Q9: 0 | R9: 0 | S9: 0 | T9: 0 | U9: 0 | V9: 0 | W9: 0 | X9: 0 | Y9: 0 | Z9: 0 | AA9: 0 | AB9: 0 | AC9: 0 | AD9: 0 | AE9: 0 | AF9: 0 | AG9: =SUM(C9:INDEX(C9:AF9,1,'Setup'!$C$8))

Sheet Risk Register
A1: RISK REGISTER — probability-weighted 3PE impacts
A2: ➕ Add → AddRisk | D2: 🗑 Delete selected → DeleteRisk
A3: Risk ID | B3: Risk Name | C3: Category | D3: Probability | E3: Min Impact | F3: Most Likely Impact | G3: Max Impact | H3: Distribution | I3: Risk Owner | J3: Include? | K3: Notes
A4: ="R"&(ROW()-3) | B4: Adverse ground conditions | C4: Technical | D4: 0.3 | E4: 20000 | F4: 45000 | G4: 90000 | H4: Triangular | I4: Civil Lead | J4: Yes
A5: ="R"&(ROW()-3) | B5: Major design change | C5: Commercial | D5: 0.4 | E5: 15000 | F5: 30000 | G5: 60000 | H5: Pert | I5: Design Mgr | J5: Yes
A6: ="R"&(ROW()-3) | B6: Material price spike | C6: Market | D6: 0.5 | E6: 10000 | F6: 25000 | G6: 55000 | H6: Triangular | I6: Procurement | J6: Yes
A7: ="R"&(ROW()-3) | B7: Schedule delay | C7: Delivery | D7: 0.25 | E7: 20000 | F7: 40000 | G7: 80000 | H7: Pert | I7: PM | J7: Yes

Sheet Risk Profiling
A1: RISK PROFILING — % per year (rows must total 100%)
A3: Risk ID | B3: Risk Name | C3: FY1 | D3: FY2 | E3: FY3 | F3: FY4 | G3: FY5 | H3: FY6 | I3: FY7 | J3: FY8 | K3: FY9 | L3: FY10 | M3: FY11 | N3: FY12 | O3: FY13 | P3: FY14 | Q3: FY15 | R3: FY16 | S3: FY17 | T3: FY18 | U3: FY19 | V3: FY20 | W3: FY21 | X3: FY22 | Y3: FY23 | Z3: FY24 | AA3: FY25 | AB3: FY26 | AC3: FY27 | AD3: FY28 | AE3: FY29 | AF3: FY30 | AG3: Total %
A4: ='Risk Register'!A4 | B4: ='Risk Register'!B4 | C4: 0.33333333 | D4: 0.26666667 | E4: 0.2 | F4: 0.13333333 | G4: 0.066666667 | H4: 0 | I4: 0 | J4: 0 | K4: 0 | L4: 0 | M4: 0 | N4: 0 | O4: 0 | P4: 0 | Q4: 0 | R4: 0 | S4: 0 | T4: 0 | U4: 0 | V4: 0 | W4: 0 | X4: 0 | Y4: 0 | Z4: 0 | AA4: 0 | AB4: 0 | AC4: 0 | AD4: 0 | AE4: 0 | AF4: 0 | AG4: =SUM(C4:INDEX(C4:AF4,1,'Setup'!$C$8))
A5: ='Risk Register'!A5 | B5: ='Risk Register'!B5 | C5: 0.11111111 | D5: 0.22222222 | E5: 0.33333333 | F5: 0.22222222 | G5: 0.11111111 | H5: 0 | I5: 0 | J5: 0 | K5: 0 | L5: 0 | M5: 0 | N5: 0 | O5: 0 | P5: 0 | Q5: 0 | R5: 0 | S5: 0 | T5: 0 | U5: 0 | V5: 0 | W5: 0 | X5: 0 | Y5: 0 | Z5: 0 | AA5: 0 | AB5: 0 | AC5: 0 | AD5: 0 | AE5: 0 | AF5: 0 | AG5: =SUM(C5:INDEX(C5:AF5,1,'Setup'!$C$8))
A6: ='Risk Register'!A6 | B6: ='Risk Register'!B6 | C6: 0.11111111 | D6: 0.22222222 | E6: 0.33333333 | F6: 0.22222222 | G6: 0.11111111 | H6: 0 | I6: 0 | J6: 0 | K6: 0 | L6: 0 | M6: 0 | N6: 0 | O6: 0 | P6: 0 | Q6: 0 | R6: 0 | S6: 0 | T6: 0 | U6: 0 | V6: 0 | W6: 0 | X6: 0 | Y6: 0 | Z6: 0 | AA6: 0 | AB6: 0 | AC6: 0 | AD6: 0 | AE6: 0 | AF6: 0 | AG6: =SUM(C6:INDEX(C6:AF6,1,'Setup'!$C$8))
A7: ='Risk Register'!A7 | B7: ='Risk Register'!B7 | C7: 0.066666667 | D7: 0.13333333 | E7: 0.2 | F7: 0.26666667 | G7: 0.33333333 | H7: 0 | I7: 0 | J7: 0 | K7: 0 | L7: 0 | M7: 0 | N7: 0 | O7: 0 | P7: 0 | Q7: 0 | R7: 0 | S7: 0 | T7: 0 | U7: 0 | V7: 0 | W7: 0 | X7: 0 | Y7: 0 | Z7: 0 | AA7: 0 | AB7: 0 | AC7: 0 | AD7: 0 | AE7: 0 | AF7: 0 | AG7: =SUM(C7:INDEX(C7:AF7,1,'Setup'!$C$8))

Sheet Inflation
A1: INFLATION — rate per year; cumulative factor compounds (FY1 = 1.0)
A3: FY | B3: Year | C3: Inflation Rate | D3: Cumulative Factor
A4: FY1 | B4: ='Setup'!$C$7+0 | C4: 0 | D4: =1
A5: FY2 | B5: ='Setup'!$C$7+1 | C5: 0.03 | D5: =D4*(1+C5)
A6: FY3 | B6: ='Setup'!$C$7+2 | C6: 0.03 | D6: =D5*(1+C6)
A7: FY4 | B7: ='Setup'!$C$7+3 | C7: 0.03 | D7: =D6*(1+C7)
A8: FY5 | B8: ='Setup'!$C$7+4 | C8: 0.03 | D8: =D7*(1+C8)
A9: FY6 | B9: ='Setup'!$C$7+5 | C9: 0.03 | D9: =D8*(1+C9)
A10: FY7 | B10: ='Setup'!$C$7+6 | C10: 0.03 | D10: =D9*(1+C10)
A11: FY8 | B11: ='Setup'!$C$7+7 | C11: 0.03 | D11: =D10*(1+C11)
A12: FY9 | B12: ='Setup'!$C$7+8 | C12: 0.03 | D12: =D11*(1+C12)
A13: FY10 | B13: ='Setup'!$C$7+9 | C13: 0.03 | D13: =D12*(1+C13)
A14: FY11 | B14: ='Setup'!$C$7+10 | C14: 0.03 | D14: =D13*(1+C14)
A15: FY12 | B15: ='Setup'!$C$7+11 | C15: 0.03 | D15: =D14*(1+C15)
A16: FY13 | B16: ='Setup'!$C$7+12 | C16: 0.03 | D16: =D15*(1+C16)
A17: FY14 | B17: ='Setup'!$C$7+13 | C17: 0.03 | D17: =D16*(1+C17)
A18: FY15 | B18: ='Setup'!$C$7+14 | C18: 0.03 | D18: =D17*(1+C18)
A19: FY16 | B19: ='Setup'!$C$7+15 | C19: 0.03 | D19: =D18*(1+C19)
A20: FY17 | B20: ='Setup'!$C$7+16 | C20: 0.03 | D20: =D19*(1+C20)
A21: FY18 | B21: ='Setup'!$C$7+17 | C21: 0.03 | D21: =D20*(1+C21)
A22: FY19 | B22: ='Setup'!$C$7+18 | C22: 0.03 | D22: =D21*(1+C22)
A23: FY20 | B23: ='Setup'!$C$7+19 | C23: 0.03 | D23: =D22*(1+C23)
A24: FY21 | B24: ='Setup'!$C$7+20 | C24: 0.03 | D24: =D23*(1+C24)
A25: FY22 | B25: ='Setup'!$C$7+21 | C25: 0.03 | D25: =D24*(1+C25)
A26: FY23 | B26: ='Setup'!$C$7+22 | C26: 0.03 | D26: =D25*(1+C26)
A27: FY24 | B27: ='Setup'!$C$7+23 | C27: 0.03 | D27: =D26*(1+C27)
A28: FY25 | B28: ='Setup'!$C$7+24 | C28: 0.03 | D28: =D27*(1+C28)
A29: FY26 | B29: ='Setup'!$C$7+25 | C29: 0.03 | D29: =D28*(1+C29)
A30: FY27 | B30: ='Setup'!$C$7+26 | C30: 0.03 | D30: =D29*(1+C30)
A31: FY28 | B31: ='Setup'!$C$7+27 | C31: 0.03 | D31: =D30*(1+C31)
A32: FY29 | B32: ='Setup'!$C$7+28 | C32: 0.03 | D32: =D31*(1+C32)
A33: FY30 | B33: ='Setup'!$C$7+29 | C33: 0.03 | D33: =D32*(1+C33)

Sheet Results
A1: RESULTS
A2: ▶ Run the simulation (Dashboard button or Alt+F8 ▸ RunSimulation) to populate these.
A4: A. Total Cost Percentiles
A5: Percentile | B5: Total Cost
A6: P10
A7: P30
A8: P50
A9: P60
A10: P70
A11: P80
A12: P90
A13: P95
A15: B. Contingency by Confidence
A16: Confidence | B16: Total Cost | C16: Base Cost | D16: Contingency | E16: Contingency %
A17: P50
A18: P70
A19: P80
A20: P90
A22: C. Annual Cash Flow by Confidence
A23: Year | B23: P50 | C23: P70 | D23: P80 | E23: P90
A56: D. NPV by Confidence
A57: Confidence | B57: Nominal Total | C57: NPV
A58: P50
A59: P70
A60: P80
A61: P90

Sheet Sensitivity
A1: SENSITIVITY (TORNADO)
A2: P90 − P10 spread of each driver's sampled value (filled by the macro).
A4: Driver | B4: Type | C4: P10 | D4: P90 | E4: Range (P90−P10)

Sheet Checks
A1: MODEL CHECKS
A4: Check | B4: Result
A5: Cost profile rows total 100% | B5: =IF(SUMPRODUCT(--(ABS('Cost Profiling'!$AG$4:$AG$9-1)>0.001))=0,"PASS","FAIL")
A6: Risk profile rows total 100% | B6: =IF(SUMPRODUCT(--(ABS('Risk Profiling'!$AG$4:$AG$7-1)>0.001))=0,"PASS","FAIL")
A7: Cost lines Min<=ML<=Max | B7: =IF(SUMPRODUCT(--('Cost Lines'!$G$4:$G$9>'Cost Lines'!$H$4:$H$9))+SUMPRODUCT(--('Cost Lines'!$H$4:$H$9>'Cost Lines'!$I$4:$I$9))=0,"PASS","FAIL")
A8: Risks Min<=ML<=Max | B8: =IF(SUMPRODUCT(--('Risk Register'!$E$4:$E$7>'Risk Register'!$F$4:$F$7))+SUMPRODUCT(--('Risk Register'!$F$4:$F$7>'Risk Register'!$G$4:$G$7))=0,"PASS","FAIL")
A9: Iterations > 0 | B9: =IF('Setup'!$C$9>0,"PASS","FAIL")
A10: Years between 1 and 30 | B10: =IF(AND('Setup'!$C$8>=1,'Setup'!$C$8<=30),"PASS","FAIL")
A11: Discount rate valid | B11: =IF(AND('Setup'!$C$11>=0,'Setup'!$C$11<0.5),"PASS","FAIL")
A13: All checks | B13: =IF(COUNTIF(B5:B11,"FAIL")=0,"ALL OK","CHECK FAILED")

Sheet ChartData
A1: Center | B1: Count | D1: Cost | E1: CumProb | G1: Year | H1: Cum P50 | I1: Cum P80
